redis_helper/__init__.py
redis_helper/collection.py
redis_helper/settings.ini
redis_helper/scripts/__init__.py
redis_helper/scripts/clear_locks.py
redis_helper/scripts/collection_reports.py
redis_helper/scripts/download_examples.py
redis_helper/scripts/download_scripts.py
redis_helper/scripts/notes.py
redis_helper/scripts/shell.py
tests/__init__.py
tests/test_collection.py
tests/test_settings.py
redis_helper-0.5.0.dist-info/LICENSE.txt
redis_helper-0.5.0.dist-info/METADATA
redis_helper-0.5.0.dist-info/WHEEL
redis_helper-0.5.0.dist-info/entry_points.txt
redis_helper-0.5.0.dist-info/top_level.txt
redis_helper-0.5.0.dist-info/RECORD
