Metadata-Version: 2.1
Name: redis-helper
Version: 0.5.0
Summary: Easily store, index, and modify Python dicts in Redis (with flexible searching)
Home-page: https://github.com/kenjyco/redis-helper
Download-URL: https://github.com/kenjyco/redis-helper/tarball/v0.5.0
Author: Ken
Author-email: kenjyco@gmail.com
License: MIT
Keywords: redis,cli,command-line,dictionary,data,database,secondary index,model,prototype,event logging,dashboard,easy modeling,helper,kenjyco
Classifier: Development Status :: 4 - Beta
Classifier: Environment :: Console
Classifier: Intended Audience :: Developers
Classifier: License :: OSI Approved :: MIT License
Classifier: Operating System :: MacOS :: MacOS X
Classifier: Operating System :: POSIX :: Linux
Classifier: Programming Language :: Python :: 3.5
Classifier: Programming Language :: Python :: 3.6
Classifier: Programming Language :: Python :: 3.7
Classifier: Programming Language :: Python :: 3.8
Classifier: Programming Language :: Python :: 3.9
Classifier: Programming Language :: Python :: 3.10
Classifier: Programming Language :: Python :: 3.11
Classifier: Programming Language :: Python :: 3.12
Classifier: Programming Language :: Python :: 3.13
Classifier: Programming Language :: Python
Classifier: Topic :: Database
Classifier: Topic :: Software Development :: Libraries
Classifier: Topic :: Utilities
License-File: LICENSE.txt
Requires-Dist: bg-helper
Requires-Dist: click (>=6.0)
Requires-Dist: dt-helper
Requires-Dist: fs-helper
Requires-Dist: input-helper
Requires-Dist: settings-helper
Requires-Dist: redis (>=3.5.3)
Requires-Dist: hiredis (>=1.1.0) ; python_version < "3.12"
Requires-Dist: ujson (==4.3.0) ; python_version == "3.6"
Requires-Dist: hiredis (>=2.1.1) ; python_version >= "3.12"
Requires-Dist: redis (>=4.1.0) ; python_version >= "3.12"
Requires-Dist: ujson (>=5.4.0) ; python_version >= "3.7"
